MANIFEST.in
README.rst
ez_setup.py
setup.py
syntrax.py
syntrax.egg-info/PKG-INFO
syntrax.egg-info/SOURCES.txt
syntrax.egg-info/dependency_links.txt
syntrax.egg-info/entry_points.txt
syntrax.egg-info/top_level.txt