Metadata-Version: 1.1
Name: syntrax
Version: 1.0
Summary: Railroad syntax diagram generator
Home-page: http://kevinpt.github.io/syntrax
Author: Kevin Thibedeau
Author-email: kevin.thibedeau@gmail.com
License: MIT
Download-URL: http://kevinpt.github.io/syntrax
Keywords: Railroad syntax diagram generator
Platform: Any
Classifier: Development Status :: 5 - Production/Stable
Classifier: Operating System :: OS Independent
Classifier: Intended Audience :: Developers
Classifier: Topic :: Multimedia :: Graphics
Classifier: Topic :: Software Development :: Documentation
Classifier: Natural Language :: English
Classifier: Programming Language :: Python :: 2.7
Classifier: Programming Language :: Python :: 3
Classifier: License :: OSI Approved :: MIT License
